snprimer/__init__.py
snprimer/__version__.py
snprimer/position_range.py
snprimer/primer.py
snprimer/primer_pair.py
snprimer/snp.py
snprimer-0.2.0.dist-info/WHEEL
snprimer-0.2.0.dist-info/METADATA
snprimer-0.2.0.dist-info/RECORD
