Metadata-Version: 2.1
Name: snprimer
Version: 0.2.0
Summary: Small python library to search snp in primer by position or by sequence.
Home-page: https://github.com/Benoitdw/SNPrimer
Author: Benoitdw
Author-email: bw@oncodna.com
Requires-Python: >=3.11,<4.0
Classifier: Programming Language :: Python :: 3
Classifier: Programming Language :: Python :: 3.11
Requires-Dist: bump2version (>=1.0.1,<2.0.0)
Requires-Dist: click (>=8.1.3,<9.0.0)
Requires-Dist: gget (>=0.3.11,<0.4.0)
Requires-Dist: myvariant (>=1.0.0,<2.0.0)
Requires-Dist: pre-commit (>=2.20.0,<3.0.0)
Requires-Dist: pyfaidx (>=0.7.1,<0.8.0)
Project-URL: Repository, https://github.com/Benoitdw/SNPrimer
